[
  {
    "id": 1,
    "title": "Select Service",
    "description": "Browse our list of services and choose the one that suits your needs.",
    "icon": "M9 12h6m-6 4h6m2 5H7a2 2 0 01-2-2V5a2 2 0 012-2h5.586a1 1 0 01.707.293l5.414 5.414a1 1 0 01.293.707V19a2 2 0 01-2 2z"
  },
  {
    "id": 2,
    "title": "Book Schedule",
    "description": "Pick a convenient date and time for our professionals to visit.",
    "icon": "M8 7V3m8 4V3m-9 8h10M5 21h14a2 2 0 002-2V7a2 2 0 00-2-2H5a2 2 0 00-2 2v12a2 2 0 002 2z"
  },
  {
    "id": 3,
    "title": "Get Served",
    "description": "Our verified expert will arrive at your doorstep and get the job done.",
    "icon": "M14.828 14.828a4 4 0 01-5.656 0M9 10h.01M15 10h.01M21 12a9 9 0 11-18 0 9 9 0 0118 0z"
  },
  {
    "id": 4,
    "title": "Pay Easily",
    "description": "Pay securely online or via cash after the service is completed.",
    "icon": "M17 9V7a2 2 0 00-2-2H5a2 2 0 00-2 2v6a2 2 0 002 2h2m2 4h10a2 2 0 002-2v-6a2 2 0 00-2-2H9a2 2 0 00-2 2v6a2 2 0 002 2zm7-5a2 2 0 11-4 0 2 2 0 014 0z"
  }
]